<Properties StartupConfiguration="{118D9CE1-97B6-4961-BAF2-F77EE6AF0EAE}|Default">
  <MonoDevelop.Ide.ItemProperties.OPerators__submission PreferredExecutionTarget="MonoDevelop.Default" />
  <MonoDevelop.Ide.ItemProperties.Operators__submission PreferredExecutionTarget="MonoDevelop.Default" />
  <MonoDevelop.Ide.Workbench ActiveDocument="OPerators_submission/Program.cs">
    <Files>
      <File FileName="OPerators_submission/Program.cs" Line="19" Column="29" />
      <File FileName="OPerators_submission/Employee.cs" Line="26" Column="25" />
    </Files>
    <Pads>
      <Pad Id="ProjectPad">
        <State name="__root__">
          <Node name="Operators_submission" expanded="True">
            <Node name="OPerators_submission" expanded="True">
              <Node name="Program.cs" selected="True" />
            </Node>
          </Node>
        </State>
      </Pad>
    </Pads>
  </MonoDevelop.Ide.Workbench>
  <MonoDevelop.Ide.DebuggingService.PinnedWatches />
  <MonoDevelop.Ide.Workspace ActiveConfiguration="Debug" />
  <MonoDevelop.Ide.DebuggingService.Breakpoints>
    <BreakpointStore />
  </MonoDevelop.Ide.DebuggingService.Breakpoints>
  <MultiItemStartupConfigurations />
</Properties>